vectorise/__init__.py
vectorise/__vector__.py
vectorise-0.0.6.dist-info/LICENSE
vectorise-0.0.6.dist-info/METADATA
vectorise-0.0.6.dist-info/WHEEL
vectorise-0.0.6.dist-info/top_level.txt
vectorise-0.0.6.dist-info/RECORD
