Metadata-Version: 2.1
Name: vectorise
Version: 0.0.6
Summary: A Python 3.x package that implements and represents basic functionalities of Vectors.
Home-page: UNKNOWN
Author: Programmin-in-Python (MK)
Author-email: <kalanithi6014@gmail.com>
License: UNKNOWN
Project-URL: GitHub, https://github.com/Programmin-in-Python/vectorise
Project-URL: Release Notes, https://github.com/Programmin-in-Python/vectorise/releases/tag/v0.0.6
Project-URL: Home Page, https://github.com/Programmin-in-Python/vectorise
Keywords: python3,vector,vectorise
Platform: UNKNOWN
Classifier: Development Status :: 5 - Production/Stable
Classifier: Intended Audience :: Science/Research
Classifier: License :: OSI Approved :: MIT License
Classifier: Natural Language :: English
Classifier: Operating System :: Unix
Classifier: Operating System :: MacOS :: MacOS X
Classifier: Operating System :: Microsoft :: Windows
Classifier: Programming Language :: Python :: 3 :: Only
Classifier: Programming Language :: Python :: 3
Classifier: Topic :: Education
Classifier: Topic :: Scientific/Engineering :: Mathematics
Classifier: Topic :: Scientific/Engineering :: Physics
Requires-Python: >=3
